MANIFEST.in
README.rst
setup.cfg
setup.py
repoze/__init__.py
repoze/what/__init__.py
repoze/what/plugins/__init__.py
repoze/what/plugins/oauth/__init__.py
repoze/who/__init__.py
repoze/who/plugins/__init__.py
repoze/who/plugins/oauth/__init__.py
repoze/who/plugins/oauth/managers.py
repoze/who/plugins/oauth/model.py
repoze/who/plugins/oauth/plugin.py
repoze_oauth_plugin.egg-info/PKG-INFO
repoze_oauth_plugin.egg-info/SOURCES.txt
repoze_oauth_plugin.egg-info/dependency_links.txt
repoze_oauth_plugin.egg-info/namespace_packages.txt
repoze_oauth_plugin.egg-info/not-zip-safe
repoze_oauth_plugin.egg-info/requires.txt
repoze_oauth_plugin.egg-info/top_level.txt