Metadata-Version: 1.0
Name: repoze-oauth-plugin
Version: 0.1.1
Summary: OAuth plugin for repoze.who and repoze.what
Home-page: UNKNOWN
Author: Linas Juškevičius
Author-email: linas.juskevicius@gmail.com
License: MIT
Keywords: auth repoze repoze.who repoze.what predicate oauth
Platform: UNKNOWN
